Metadata-Version: 1.1
Name: jcms
Version: 1.2.0
Summary: This is a cms written in Django and made by JCB Development
Home-page: https://github.com/jessielaf/jcms
Author: Jessie Liauw A Fong
Author-email: jessielaff@live.nl
License: MIT
Keywords: cms admin development content management system
Platform: UNKNOWN
Classifier: Development Status :: 5 - Production/Stable
Classifier: Intended Audience :: Developers
Classifier: Topic :: Internet :: WWW/HTTP :: Site Management
Classifier: License :: OSI Approved :: MIT License
Classifier: Programming Language :: Python :: 3.5
Classifier: Framework :: Django :: 2.0
